Metadata-Version: 2.1
Name: odoo11-addon-mis-builder
Version: 11.0.3.6.9
Summary: Build 'Management Information System' Reports and Dashboards
Home-page: https://github.com/OCA/mis-builder
Author: ACSONE SA/NV, Odoo Community Association (OCA)
Author-email: support@odoo-community.org
License: AGPL-3
Platform: UNKNOWN
Classifier: Programming Language :: Python
Classifier: Framework :: Odoo
Classifier: Framework :: Odoo :: 11.0
Classifier: License :: OSI Approved :: GNU Affero General Public License v3
Classifier: Development Status :: 5 - Production/Stable
Requires-Python: >=2.7, !=3.0.*, !=3.1.*, !=3.2.*, !=3.3.*, !=3.4.*
Requires-Dist: odoo11-addon-date-range
Requires-Dist: odoo11-addon-report-xlsx
Requires-Dist: odoo11-addon-web-widget-color
Requires-Dist: odoo (<11.1dev,>=11.0a)
